nutritious/__init__.py
nutritious/__main__.py
nutritious-0.1.2.dist-info/LICENSE
nutritious-0.1.2.dist-info/METADATA
nutritious-0.1.2.dist-info/WHEEL
nutritious-0.1.2.dist-info/RECORD
