Metadata-Version: 2.1
Name: nutritious
Version: 0.1.2
Summary: A jsx-preprocessor for Python which enables the coder to write JSX directly in Python 🗿
Home-page: https://github.com/itsmeadarsh2008/nutritious
License: GPL
Keywords: jsx,nutritious,preprocessor,python,jsx-python,jsx-py,jsx-preprocessor,jsx-transpiler,jsx-compiler,jsx-parser,jsx-renderer,jsx-generator,jsx-transformer,jsx-converter,jsx-translation,jsx-translation-tool,jsx-to-python,jsx-in-python,jsx-for-python,jsx-python-integration,jsx-python-support,python-jsx,py-jsx,python-jsx-preprocessor,python-jsx-transpiler,python-jsx-compiler,python-jsx-parser,python-jsx-renderer,python-jsx-generator,python-jsx-transformer,python-jsx-converter,python-jsx-tran
Author: Adarsh Gourab Mahalik
Author-email: gourabmahalikadarsh@gmail.com
Requires-Python: >=3.9,<4.0
Classifier: License :: Other/Proprietary License
Classifier: Programming Language :: Python :: 3
Classifier: Programming Language :: Python :: 3.9
Classifier: Programming Language :: Python :: 3.10
Classifier: Programming Language :: Python :: 3.11
Classifier: Programming Language :: Python :: 3.12
Requires-Dist: pyPEG2 (>=2.15.2,<3.0.0)
Project-URL: Bug Tracker, https://github.com/itsmeadarsh2008/nutritious/issues
Project-URL: Repository, https://github.com/itsmeadarsh2008/nutritious.git
